{
  "resourceType": "Observation",
  "id": "FoerderungBeispiel",
  "meta": {
    "profile": [
      "https://www.oegd.de/fhir/seu/StructureDefinition/Foerderung"
    ]
  },
  "status": "final",
  "subject": {
    "reference": "Patient/PersonBeispiel"
  },
  "code": {
    "coding": [
      {
        "code": "sonstige",
        "system": "https://www.oegd.de/fhir/seu/CodeSystem/FoerderungCS",
        "display": "Sonstige Förderung"
      }
    ]
  },
  "valueCodeableConcept": {
    "coding": [
      {
        "code": "nein",
        "system": "https://www.oegd.de/fhir/seu/CodeSystem/FoerderungStatusCS",
        "display": "Nein"
      }
    ]
  }
}
