{
  "resourceType": "ValueSet",
  "status": "draft",
  "name": "SEU_UB_RotaimpfungVS",
  "id": "seu-ub-rotaimpfung-vs",
  "title": "SEU_UB_Rotaimpfung ValueSet",
  "description": "ValueSet, das verschiedene Rotavirus-Impfstoffe enthält.",
  "url": "https://www.oegd.de/fhir/seu/ValueSet/seu-ub-rotaimpfung-vs",
  "expansion": {
    "timestamp": "2024-09-10T12:00:00+00:00",
    "contains": [
      {
        "system": "https://www.oegd.de/fhir/seu/CodeSystem/seu-ub-rotaimpfung-cs",
        "code": "keine_Impfung",
        "display": "Keine Impfung"
      },
      {
        "system": "https://www.oegd.de/fhir/seu/CodeSystem/seu-ub-rotaimpfung-cs",
        "code": "Rotarix",
        "display": "Rotarix"
      },
      {
        "system": "https://www.oegd.de/fhir/seu/CodeSystem/seu-ub-rotaimpfung-cs",
        "code": "RotaTeq",
        "display": "RotaTeq"
      }
    ]
  },
  "compose": {
    "include": [
      {
        "system": "https://www.oegd.de/fhir/seu/CodeSystem/seu-ub-rotaimpfung-cs"
      }
    ]
  }
}
