{
  "resourceType": "ValueSet",
  "status": "draft",
  "name": "AuffaelligkeitVerhaltenVS",
  "id": "AuffaelligkeitVerhaltenVS",
  "title": "AuffaelligkeitVerhaltenVS",
  "description": "AuffaelligkeitVerhaltenVS",
  "version": "0.1.0",
  "url": "https://www.oegd.de/fhir/seu/ValueSet/AuffaelligkeitVerhaltenVS",
  "expansion": {
    "timestamp": "2024-04-04T10:40:04+00:00",
    "contains": [
      {
        "system": "https://www.oegd.de/fhir/seu/CodeSystem/AuffaelligkeitVerhaltenCS",
        "code": "konzentrationsstörung",
        "display": "Konzentrationsstörung"
      },
      {
        "system": "https://www.oegd.de/fhir/seu/CodeSystem/AuffaelligkeitVerhaltenCS",
        "code": "bettnässen",
        "display": "Bettnässen"
      },
      {
        "system": "https://www.oegd.de/fhir/seu/CodeSystem/AuffaelligkeitVerhaltenCS",
        "code": "einkoten",
        "display": "Einkoten"
      },
      {
        "system": "https://www.oegd.de/fhir/seu/CodeSystem/AuffaelligkeitVerhaltenCS",
        "code": "ängstlichkeit",
        "display": "Ängstlichkeit"
      },
      {
        "system": "https://www.oegd.de/fhir/seu/CodeSystem/AuffaelligkeitVerhaltenCS",
        "code": "aggressivität",
        "display": "Aggressivität"
      },
      {
        "system": "https://www.oegd.de/fhir/seu/CodeSystem/AuffaelligkeitVerhaltenCS",
        "code": "schlafstörung",
        "display": "Schlafstörung"
      },
      {
        "system": "https://www.oegd.de/fhir/seu/CodeSystem/AuffaelligkeitVerhaltenCS",
        "code": "hyperaktivität",
        "display": "Motorische Unruhe/Hyperaktivität"
      },
      {
        "system": "https://www.oegd.de/fhir/seu/CodeSystem/AuffaelligkeitVerhaltenCS",
        "code": "riskantes_handeln",
        "display": "Riskantes Handeln"
      },
      {
        "system": "https://www.oegd.de/fhir/seu/CodeSystem/AuffaelligkeitVerhaltenCS",
        "code": "schlechter_appetit",
        "display": "Schlechter Appetit"
      },
      {
        "system": "https://www.oegd.de/fhir/seu/CodeSystem/AuffaelligkeitVerhaltenCS",
        "code": "wenig_ausdauer_beim_spielen",
        "display": "Wenig Ausdauer beim Spielen"
      },
      {
        "system": "https://www.oegd.de/fhir/seu/CodeSystem/AuffaelligkeitVerhaltenCS",
        "code": "spät_gesprochen",
        "display": "Spät gesprochen"
      },
      {
        "system": "https://www.oegd.de/fhir/seu/CodeSystem/AuffaelligkeitVerhaltenCS",
        "code": "neigung_zum_erbrechen",
        "display": "Neigung zum Erbrechen"
      },
      {
        "system": "https://www.oegd.de/fhir/seu/CodeSystem/AuffaelligkeitVerhaltenCS",
        "code": "kann_nicht_zuhören",
        "display": "Kann nicht zuhören"
      },
      {
        "system": "https://www.oegd.de/fhir/seu/CodeSystem/AuffaelligkeitVerhaltenCS",
        "code": "noch_sprachschwierigkeiten",
        "display": "Noch Sprachschwierigkeiten"
      },
      {
        "system": "https://www.oegd.de/fhir/seu/CodeSystem/AuffaelligkeitVerhaltenCS",
        "code": "häufig_bauchschmerzen",
        "display": "Häufig Bauchschmerzen"
      },
      {
        "system": "https://www.oegd.de/fhir/seu/CodeSystem/AuffaelligkeitVerhaltenCS",
        "code": "regt_sich_schnell_auf",
        "display": "Regt sich schnell auf"
      },
      {
        "system": "https://www.oegd.de/fhir/seu/CodeSystem/AuffaelligkeitVerhaltenCS",
        "code": "ungeschicklichkeit_beim_malen",
        "display": "Ungeschicklichkeit beim Malen"
      },
      {
        "system": "https://www.oegd.de/fhir/seu/CodeSystem/AuffaelligkeitVerhaltenCS",
        "code": "zerstört_viel_spielzeug",
        "display": "Zerstört viel Spielzeug"
      },
      {
        "system": "https://www.oegd.de/fhir/seu/CodeSystem/AuffaelligkeitVerhaltenCS",
        "code": "benutzen_der_linken_hand",
        "display": "Benutzen der linken Hand"
      },
      {
        "system": "https://www.oegd.de/fhir/seu/CodeSystem/AuffaelligkeitVerhaltenCS",
        "code": "nägel_knabbern",
        "display": "Nägel knabbern"
      },
      {
        "system": "https://www.oegd.de/fhir/seu/CodeSystem/AuffaelligkeitVerhaltenCS",
        "code": "ist_schnell_entmutigt",
        "display": "Ist schnell entmutigt"
      },
      {
        "system": "https://www.oegd.de/fhir/seu/CodeSystem/AuffaelligkeitVerhaltenCS",
        "code": "häufiges_hinfallen",
        "display": "Häufiges Hinfallen"
      },
      {
        "system": "https://www.oegd.de/fhir/seu/CodeSystem/AuffaelligkeitVerhaltenCS",
        "code": "großer_bewegungsdrang",
        "display": "Großer Bewegungsdrang"
      },
      {
        "system": "https://www.oegd.de/fhir/seu/CodeSystem/AuffaelligkeitVerhaltenCS",
        "code": "kann_sich_schlecht_an_regeln_halten",
        "display": "Kann sich schlecht an Regeln halten"
      },
      {
        "system": "https://www.oegd.de/fhir/seu/CodeSystem/AuffaelligkeitVerhaltenCS",
        "code": "riskante_handlungen",
        "display": "unüberlegte/riskante Handlungen"
      }
    ]
  },
  "compose": {
    "include": [
      {
        "system": "https://www.oegd.de/fhir/seu/CodeSystem/AuffaelligkeitVerhaltenCS"
      }
    ]
  }
}
